[
    {
        "name": "Aggeneys parkrun",
        "reason": "Shortage of volunteers",
        "date": "2025-10-04"
    },
    {
        "name": "Alexandra parkrun, Moss Side",
        "reason": "Course unsafe or blocked",
        "date": "2025-10-04"
    },
    {
        "name": "Aronica’s Nursery parkrun",
        "reason": "Shortage of volunteers",
        "date": "2025-10-04"
    },
    {
        "name": "Auburn Botanic Gardens parkrun",
        "reason": "Venue unavailable",
        "date": "2025-10-04"
    },
    {
        "name": "Ballinamore Greenway parkrun",
        "reason": "Course unsafe or blocked",
        "date": "2025-10-04"
    },
    {
        "name": "Beacon parkrun",
        "reason": "Shortage of volunteers",
        "date": "2025-10-04"
    },
    {
        "name": "Bedworth parkrun",
        "reason": "Course unsafe or blocked",
        "date": "2025-10-04"
    },
    {
        "name": "Birchwood Trails parkrun",
        "reason": "Venue unavailable",
        "date": "2025-10-04"
    },
    {
        "name": "Botanical Garden parkrun",
        "reason": "Venue unavailable",
        "date": "2025-10-04"
    },
    {
        "name": "Brockhole on Windermere junior parkrun",
        "reason": "Venue unavailable",
        "date": "2025-10-05"
    },
    {
        "name": "Brooklands parkrun",
        "reason": "Venue unavailable",
        "date": "2025-10-04"
    },
    {
        "name": "Burnage parkrun",
        "reason": "Course unsafe or blocked",
        "date": "2025-10-04"
    },
    {
        "name": "Burswood Peninsula parkrun",
        "reason": "Venue unavailable",
        "date": "2025-10-04"
    },
    {
        "name": "Carlisle junior parkrun",
        "reason": "Venue unavailable",
        "date": "2025-10-05"
    },
    {
        "name": "Castleblayney parkrun",
        "reason": "Venue unavailable",
        "date": "2025-10-04"
    },
    {
        "name": "Castlerea parkrun",
        "reason": "Course unsafe or blocked",
        "date": "2025-10-04"
    },
    {
        "name": "Chaffey Park parkrun",
        "reason": "Shortage of volunteers",
        "date": "2025-10-04"
    },
    {
        "name": "Clashduv junior parkrun",
        "reason": "Shortage of volunteers",
        "date": "2025-10-05"
    },
    {
        "name": "Clougha Pike parkrun",
        "reason": "Course unsafe or blocked",
        "date": "2025-10-04"
    },
    {
        "name": "Coal Creek Trail parkrun",
        "reason": "Venue unavailable",
        "date": "2025-10-04"
    },
    {
        "name": "Cockermouth Greenway parkrun",
        "reason": "Course unsafe or blocked",
        "date": "2025-10-04"
    },
    {
        "name": "Con Smith parkrun",
        "reason": "Course unsafe or blocked",
        "date": "2025-10-04"
    },
    {
        "name": "Cootehill parkrun",
        "reason": "Course unsafe or blocked",
        "date": "2025-10-04"
    },
    {
        "name": "Crinan Canal parkrun",
        "reason": "Course unsafe or blocked",
        "date": "2025-10-04"
    },
    {
        "name": "Cycle Route 43 parkrun, Ystalyfera",
        "reason": "Course unsafe or blocked",
        "date": "2025-10-04"
    },
    {
        "name": "Darndale parkrun",
        "reason": "Course unsafe or blocked",
        "date": "2025-10-04"
    },
    {
        "name": "Deep Run parkrun",
        "reason": "Venue unavailable",
        "date": "2025-10-04"
    },
    {
        "name": "Deerpark Forest parkrun, Virginia",
        "reason": "Course unsafe or blocked",
        "date": "2025-10-04"
    },
    {
        "name": "Duikersdrift parkrun, Tulbagh",
        "reason": "Venue unavailable",
        "date": "2025-10-04"
    },
    {
        "name": "Eastbourne junior parkrun",
        "reason": "Course unsafe or blocked",
        "date": "2025-10-05"
    },
    {
        "name": "Elder Park junior parkrun",
        "reason": "Shortage of volunteers",
        "date": "2025-10-05"
    },
    {
        "name": "Elgin parkrun",
        "reason": "Shortage of volunteers",
        "date": "2025-10-04"
    },
    {
        "name": "Erddig parkrun",
        "reason": "Venue unavailable",
        "date": "2025-10-04"
    },
    {
        "name": "Flatts Lane parkrun",
        "reason": "Course unsafe or blocked",
        "date": "2025-10-04"
    },
    {
        "name": "Fletcher Moss parkrun",
        "reason": "Course unsafe or blocked",
        "date": "2025-10-04"
    },
    {
        "name": "Ford parkrun",
        "reason": "Venue unavailable",
        "date": "2025-10-04"
    },
    {
        "name": "Forest Rec junior parkrun",
        "reason": "Venue unavailable",
        "date": "2025-10-05"
    },
    {
        "name": "Forfar Loch parkrun",
        "reason": "Course unsafe or blocked",
        "date": "2025-10-04"
    },
    {
        "name": "Futakotamagawa parkrun",
        "reason": "Venue unavailable",
        "date": "2025-10-04"
    },
    {
        "name": "Ganavan Sands parkrun",
        "reason": "Course unsafe or blocked",
        "date": "2025-10-04"
    },
    {
        "name": "Gateshead parkrun",
        "reason": "Course unsafe or blocked",
        "date": "2025-10-04"
    },
    {
        "name": "Glenfarne Wood parkrun",
        "reason": "Course unsafe or blocked",
        "date": "2025-10-04"
    },
    {
        "name": "Great Yarmouth North Beach parkrun",
        "reason": "Shortage of volunteers",
        "date": "2025-10-04"
    },
    {
        "name": "Harlow parkrun",
        "reason": "Course unsafe or blocked",
        "date": "2025-10-04"
    },
    {
        "name": "Harrismith parkrun",
        "reason": "Event Closed",
        "date": "2025-10-04"
    },
    {
        "name": "Holyrood parkrun",
        "reason": "Course unsafe or blocked",
        "date": "2025-10-04"
    },
    {
        "name": "Hoërskool Ben Viljoen parkrun",
        "reason": "Shortage of volunteers",
        "date": "2025-10-04"
    },
    {
        "name": "Hyde parkrun",
        "reason": "Course unsafe or blocked",
        "date": "2025-10-04"
    },
    {
        "name": "Innesfree Park parkrun",
        "reason": "Venue unavailable",
        "date": "2025-10-04"
    },
    {
        "name": "Joe Creason parkrun",
        "reason": "Venue unavailable",
        "date": "2025-10-04"
    },
    {
        "name": "Kralinbergh parkrun",
        "reason": "Shortage of volunteers",
        "date": "2025-10-04"
    },
    {
        "name": "Laytown Beach parkrun",
        "reason": "Course unsafe or blocked",
        "date": "2025-10-04"
    },
    {
        "name": "Lees Road parkrun",
        "reason": "Course unsafe or blocked",
        "date": "2025-10-04"
    },
    {
        "name": "Limerick parkrun",
        "reason": "Course unsafe or blocked",
        "date": "2025-10-04"
    },
    {
        "name": "Llanishen Park parkrun",
        "reason": "Course unsafe or blocked",
        "date": "2025-10-04"
    },
    {
        "name": "Longford parkrun",
        "reason": "Course unsafe or blocked",
        "date": "2025-10-04"
    },
    {
        "name": "Lough Key parkrun",
        "reason": "Course unsafe or blocked",
        "date": "2025-10-04"
    },
    {
        "name": "Magherafelt junior parkrun",
        "reason": "Course unsafe or blocked",
        "date": "2025-10-05"
    },
    {
        "name": "Mallards Pike parkrun",
        "reason": "Venue unavailable",
        "date": "2025-10-04"
    },
    {
        "name": "Marine Parade parkrun",
        "reason": "Course Unavailable - Beach Race",
        "date": "2025-10-04"
    },
    {
        "name": "Millennium parkrun",
        "reason": "Shortage of volunteers",
        "date": "2025-10-04"
    },
    {
        "name": "Morrinsville Recreation Ground parkrun",
        "reason": "Venue unavailable",
        "date": "2025-10-04"
    },
    {
        "name": "Mtunzini parkrun",
        "reason": "Venue unavailable",
        "date": "2025-10-04"
    },
    {
        "name": "Nagaragawa koen parkrun",
        "reason": "Venue unavailable",
        "date": "2025-10-04"
    },
    {
        "name": "Nathalia Showgrounds parkrun",
        "reason": "Venue unavailable",
        "date": "2025-10-04"
    },
    {
        "name": "Naturlehrpfad parkrun, Wetzlar",
        "reason": "Shortage of volunteers",
        "date": "2025-10-03"
    },
    {
        "name": "New Earswick parkrun",
        "reason": "Venue unavailable",
        "date": "2025-10-04"
    },
    {
        "name": "Noel Booth Community parkrun",
        "reason": "Venue unavailable",
        "date": "2025-10-04"
    },
    {
        "name": "Offenthal parkrun",
        "reason": "Venue unavailable",
        "date": "2025-10-04"
    },
    {
        "name": "Onderstepoort Campus parkrun",
        "reason": "Venue unavailable",
        "date": "2025-10-04"
    },
    {
        "name": "Osterley junior parkrun",
        "reason": "Course unsafe or blocked",
        "date": "2025-10-05"
    },
    {
        "name": "Paisley Park parkrun",
        "reason": "Course unsafe or blocked",
        "date": "2025-10-04"
    },
    {
        "name": "Pallara parkrun",
        "reason": "Venue unavailable",
        "date": "2025-10-04"
    },
    {
        "name": "Park View junior parkrun",
        "reason": "Venue unavailable",
        "date": "2025-10-05"
    },
    {
        "name": "Peel parkrun",
        "reason": "Venue unavailable",
        "date": "2025-10-04"
    },
    {
        "name": "Penrith Lakes parkrun",
        "reason": "Venue unavailable",
        "date": "2025-10-04"
    },
    {
        "name": "Peoples Park junior parkrun",
        "reason": "Shortage of volunteers",
        "date": "2025-10-05"
    },
    {
        "name": "Piet Retief parkrun",
        "reason": "Venue unavailable",
        "date": "2025-10-04"
    },
    {
        "name": "Pittsworth parkrun",
        "reason": "Venue unavailable",
        "date": "2025-10-04"
    },
    {
        "name": "Plas Newydd junior parkrun",
        "reason": "Venue unavailable",
        "date": "2025-10-05"
    },
    {
        "name": "Plean parkrun",
        "reason": "Course unsafe or blocked",
        "date": "2025-10-04"
    },
    {
        "name": "Pontypridd parkrun",
        "reason": "Venue unavailable",
        "date": "2025-10-04"
    },
    {
        "name": "Queen’s Parade junior parkrun, Aldershot",
        "reason": "Rushmoor 10k",
        "date": "2025-10-05"
    },
    {
        "name": "Riverside parkrun, Kamloops",
        "reason": "Venue unavailable",
        "date": "2025-10-04"
    },
    {
        "name": "Roosevelt Island DC parkrun",
        "reason": "Course unsafe or blocked",
        "date": "2025-10-04"
    },
    {
        "name": "Root 44 parkrun",
        "reason": "Permission issue",
        "date": "2025-10-04"
    },
    {
        "name": "Rosehill Victoria junior parkrun",
        "reason": "Shortage of volunteers",
        "date": "2025-10-05"
    },
    {
        "name": "Ross-on-Wye parkrun",
        "reason": "Course unsafe or blocked",
        "date": "2025-10-04"
    },
    {
        "name": "SHAPE parkrun",
        "reason": "Shortage of volunteers",
        "date": "2025-10-04"
    },
    {
        "name": "Sedgefield parkrun",
        "reason": "Course unsafe or blocked",
        "date": "2025-10-04"
    },
    {
        "name": "Settlers Park parkrun",
        "reason": "Shortage of volunteers",
        "date": "2025-10-04"
    },
    {
        "name": "Shaw Cherry Hill Farm parkrun",
        "reason": "Venue unavailable",
        "date": "2025-10-04"
    },
    {
        "name": "Shrewsbury parkrun",
        "reason": "Venue unavailable",
        "date": "2025-10-04"
    },
    {
        "name": "Stavanger parkrun",
        "reason": "Course unsafe or blocked",
        "date": "2025-10-04"
    },
    {
        "name": "Stormont parkrun",
        "reason": "Venue unavailable",
        "date": "2025-10-04"
    },
    {
        "name": "Telford parkrun",
        "reason": "Course unsafe or blocked",
        "date": "2025-10-04"
    },
    {
        "name": "The Waterfront junior parkrun",
        "reason": "Venue unavailable",
        "date": "2025-10-05"
    },
    {
        "name": "Tollcross parkrun, Glasgow",
        "reason": "Course unsafe or blocked",
        "date": "2025-10-04"
    },
    {
        "name": "Tsujido kaihin koen parkrun",
        "reason": "Venue unavailable",
        "date": "2025-10-04"
    },
    {
        "name": "Vaal Marina parkrun",
        "reason": "Venue unavailable",
        "date": "2025-10-04"
    },
    {
        "name": "Victoria parkrun, Truro",
        "reason": "Course unsafe or blocked",
        "date": "2025-10-04"
    },
    {
        "name": "Wakefield Thornes parkrun",
        "reason": "Course unsafe or blocked",
        "date": "2025-10-04"
    },
    {
        "name": "Walvis Bay parkrun",
        "reason": "Venue unavailable",
        "date": "2025-10-04"
    },
    {
        "name": "Whitehaven parkrun",
        "reason": "Course unsafe or blocked",
        "date": "2025-10-04"
    },
    {
        "name": "Whitfords Nodes parkrun",
        "reason": "Course unsafe or blocked",
        "date": "2025-10-04"
    },
    {
        "name": "Wollaton Hall parkrun",
        "reason": "Venue unavailable",
        "date": "2025-10-04"
    },
    {
        "name": "Y Promenâd parkrun, Aberhonddu",
        "reason": "Course unsafe or blocked",
        "date": "2025-10-04"
    },
    {
        "name": "parkrun Szczecinek",
        "reason": "Venue unavailable",
        "date": "2025-10-04"
    },
    {
        "name": "Ōroua River Walkway parkrun",
        "reason": "Venue unavailable",
        "date": "2025-10-04"
    }
]